{"cameraMode":{"drawMode":0,"name":"Shaded","section":"Shading Mode"},"sceneLighting":false,"audioPlay":false,"sceneViewState":{"m_AlwaysRefresh":false,"showFog":true,"showSkybox":false,"showFlares":true,"showImageEffects":true,"showParticleSystems":true,"showVisualEffectGraphs":true,"m_FxEnabled":true},"in2DMode":false,"pivot":{"x":-12.806205749511719,"y":12.913267135620118,"z":-11.549612045288086},"rotation":{"x":0.10583948343992233,"y":0.8460791110992432,"z":-0.18299393355846406,"w":0.48938849568367007},"size":8.023951530456543,"orthographic":false}